{"ongoing_trials": {}, "hyperparameters": {"space": [{"class_name": "Int", "config": {"name": "units", "default": null, "conditions": [], "min_value": 32, "max_value": 512, "step": 32, "sampling": "linear"}}, {"class_name": "Choice", "config": {"name": "activation", "default": "relu", "conditions": [], "values": ["relu", "tanh"], "ordered": false}}, {"class_name": "Boolean", "config": {"name": "dropout", "default": false, "conditions": []}}, {"class_name": "Float", "config": {"name": "lr", "default": 0.0001, "conditions": [], "min_value": 0.0001, "max_value": 0.01, "step": null, "sampling": "log"}}], "values": {"units": 32, "activation": "relu", "dropout": false, "lr": 0.0001}}, "start_order": ["0", "1", "2"], "end_order": ["0", "1", "2"], "run_times": {"0": 1, "1": 1, "2": 1}, "retry_queue": [], "seed": 5052, "seed_state": 5064, "tried_so_far": ["18e368a3b44a8acd8ce651a74a328c6f", "dec949e942a5e6dcbed84a49ba406215", "52251ef5d64c4543f330cfbbcf328dbe"], "id_to_hash": {"0": "52251ef5d64c4543f330cfbbcf328dbe", "1": "dec949e942a5e6dcbed84a49ba406215", "2": "18e368a3b44a8acd8ce651a74a328c6f"}, "display": {"search_start": "2023-11-13T15:07:39.162272", "trial_start": {"0": "2023-11-13T15:07:39.162272", "1": "2023-11-13T15:07:54.226679", "2": "2023-11-13T15:08:11.130841"}, "trial_number": {"0": 1, "1": 2, "2": 3}}}